{"classname": "2018金融学(中外合作办学)2班", "dateinfo": "2020-09-14", "Monday": [{"course_name": "商业银行经营学", "class_room": "国际203", "section": "1", "teacher": "康健 ", "week": "1-8周", "week_array": ["1", "2", "3", "4", "5", "6", "7", "8"]}, {"course_name": "应用文写作", "class_room": "国际212", "section": "3", "teacher": "李航宇 ", "week": "1-8,10-13周", "week_array": ["1", "2", "3", "4", "5", "6", "7", "8", "10", "11", "12", "13"]}, {"course_name": "音乐", "class_room": "博明楼(五教)2楼阶梯", "section": "5", "teacher": "陈依美智 ", "week": "1-8,10-17周", "week_array": ["1", "2", "3", "4", "5", "6", "7", "8", "10", "11", "12", "13", "14", "15", "16", "17"]}], "Tuesday": [{"course_name": "微观经济学", "class_room": "德润楼(国际)401", "section": "1", "teacher": "张翀 ", "week": "1-16周", "week_array": ["1", "2", "3", "4", "5", "6", "7", "8", "9", "10", "11", "12", "13", "14", "15", "16"]}, {"course_name": "银行与金融市场", "class_room": "国际207", "section": "2", "teacher": "Rob ", "week": "1-16周", "week_array": ["1", "2", "3", "4", "5", "6", "7", "8", "9", "10", "11", "12", "13", "14", "15", "16"]}, {"course_name": "商业银行经营学", "class_room": "博文楼南709", "section": "3", "teacher": "康健 ", "week": "5-8周", "week_array": ["5", "6", "7", "8"]}], "Wednesday": [{"course_name": "商业银行经营学", "class_room": "德润楼(国际)518", "section": "2", "teacher": "康健 ", "week": "1-8周", "week_array": ["1", "2", "3", "4", "5", "6", "7", "8"]}, {"course_name": "统计学原理", "class_room": "德润楼(国际)403", "section": "4", "teacher": "吴凤姣 ", "week": "1-8,10-17周", "week_array": ["1", "2", "3", "4", "5", "6", "7", "8", "10", "11", "12", "13", "14", "15", "16", "17"]}], "Thursday": [{"course_name": "微观经济学", "class_room": "德润楼(国际)403", "section": "1", "teacher": "张翀 ", "week": "1-16周", "week_array": ["1", "2", "3", "4", "5", "6", "7", "8", "9", "10", "11", "12", "13", "14", "15", "16"]}, {"course_name": "银行与金融市场", "class_room": "国际207", "section": "2", "teacher": "Rob ", "week": "1-16周", "week_array": ["1", "2", "3", "4", "5", "6", "7", "8", "9", "10", "11", "12", "13", "14", "15", "16"]}], "Friday": [{"course_name": "金融学I", "class_room": "国际215", "section": "1", "teacher": "Christopher Farook Hussain ", "week": "1-16周", "week_array": ["1", "2", "3", "4", "5", "6", "7", "8", "9", "10", "11", "12", "13", "14", "15", "16"]}], "Saturday": [], "Sunday": []}